poetry_partifact_plugin/__init__.py
poetry_partifact_plugin/plugin.py
poetry_partifact_plugin-0.1.1.dist-info/LICENSE
poetry_partifact_plugin-0.1.1.dist-info/WHEEL
poetry_partifact_plugin-0.1.1.dist-info/METADATA
poetry_partifact_plugin-0.1.1.dist-info/entry_points.txt
poetry_partifact_plugin-0.1.1.dist-info/RECORD
