Metadata-Version: 2.1
Name: poetry-partifact-plugin
Version: 0.1.1
Summary: A poetry plugin that configures AWS CodeArtifact
Home-page: https://github.com/aminohealth/poetry-partifact-plugin
Author: Amino Engineering Team
Author-email: eng@amino.com
Requires-Python: >=3.8,<4.0
Classifier: Programming Language :: Python :: 3
Classifier: Programming Language :: Python :: 3.8
Classifier: Programming Language :: Python :: 3.9
Classifier: Programming Language :: Python :: 3.10
Classifier: Programming Language :: Python :: 3.11
Requires-Dist: partifact (>=0.2.0,<0.3.0)
